<?xml version="1.0" encoding="utf-8"?>
<ArrayOfHuman xmlns:xsi="http://www.w3.org/2001/XMLSchema-instance" xmlns:xsd="http://www.w3.org/2001/XMLSchema">
  <Human>
    <Name>Bella</Name>
    <Age>24</Age>
    <Asal>Kediri</Asal>
  </Human>
  <Human>
    <Name>Alex</Name>
    <Age>22</Age>
    <Asal>Kediri</Asal>
  </Human>
  <Human>
    <Name>Rizky</Name>
    <Age>24</Age>
    <Asal>Bandung</Asal>
  </Human>
  <Human>
    <Name>Fadl</Name>
    <Age>24</Age>
    <Asal>Jakarta</Asal>
  </Human>
  <Human>
    <Name>Dewi</Name>
    <Age>25</Age>
    <Asal>Pati</Asal>
  </Human>
  <Human>
    <Name>Wulan</Name>
    <Age>29</Age>
    <Asal>Bandung</Asal>
  </Human>
  <Human>
    <Name>Jun</Name>
    <Age>23</Age>
    <Asal>Balikpapan</Asal>
  </Human>
  <Human>
    <Name>Yusa</Name>
    <Age>26</Age>
    <Asal>Tulungagung</Asal>
  </Human>
  <Human>
    <Name>hana</Name>
    <Age>8</Age>
    <Asal>k</Asal>
  </Human>
</ArrayOfHuman>